gimgurpython/__init__.py
gimgurpython/client.py
gimgurpython/helpers/__init__.py
gimgurpython/helpers/error.py
gimgurpython/helpers/format.py
gimgurpython/imgur/__init__.py
gimgurpython/imgur/models/__init__.py
gimgurpython/imgur/models/account.py
gimgurpython/imgur/models/account_settings.py
gimgurpython/imgur/models/album.py
gimgurpython/imgur/models/comment.py
gimgurpython/imgur/models/conversation.py
gimgurpython/imgur/models/custom_gallery.py
gimgurpython/imgur/models/gallery_album.py
gimgurpython/imgur/models/gallery_image.py
gimgurpython/imgur/models/image.py
gimgurpython/imgur/models/message.py
gimgurpython/imgur/models/notification.py
gimgurpython/imgur/models/tag.py
gimgurpython/imgur/models/tag_vote.py
gimgurpython-0.0.4.dist-info/DESCRIPTION.rst
gimgurpython-0.0.4.dist-info/METADATA
gimgurpython-0.0.4.dist-info/RECORD
gimgurpython-0.0.4.dist-info/WHEEL
gimgurpython-0.0.4.dist-info/metadata.json
gimgurpython-0.0.4.dist-info/top_level.txt
