Metadata-Version: 2.0
Name: gimgurpython
Version: 0.0.4
Summary: A fork of Official Imgur python library with OAuth2 and samples, modified as it seems not maintained anymore
Home-page: https://github.com/gmolveau/imgurpython
Author: Imgur Inc. (+ gmolveau)
Author-email: api@imgur.com
License: MIT
Keywords: api,imgur,client
Platform: UNKNOWN
Classifier: Development Status :: 4 - Beta
Classifier: Intended Audience :: Developers
Classifier: License :: OSI Approved :: MIT License
Classifier: Programming Language :: Python :: 2.7
Classifier: Programming Language :: Python :: 3
Classifier: Programming Language :: Python :: 3.2
Classifier: Programming Language :: Python :: 3.3
Classifier: Programming Language :: Python :: 3.4
Requires-Dist: requests
